{
  "location": {
    "githubOwner": "Ebmtranceboy",
    "githubRepo": "purescript-geometry-plane"
  },
  "published": {
    "1.0.2": {
      "bytes": 4687,
      "hash": "sha256-vtHIBJd0q6DEF5sgbLRznM1cIpPruV48KrJ/V4yX+xM=",
      "publishedTime": "2021-11-21T11:13:19.0Z",
      "ref": "v1.0.2"
    },
    "1.0.3": {
      "bytes": 4579,
      "hash": "sha256-oTG5SD9wOdBx2GeE2iMFriTfsSIxUIqs31CaoTxY9Yw=",
      "publishedTime": "2022-05-06T14:37:58.0Z",
      "ref": "v1.0.3"
    }
  },
  "unpublished": {}
}
