{
  "location": {
    "githubOwner": "matthew-hilty",
    "githubRepo": "purescript-higher-order"
  },
  "published": {
    "0.1.0": {
      "bytes": 12443,
      "hash": "sha256-GvOfui8KyRqv3SMLqTc7IghjtdXBuK28vs0lMcf+EiM=",
      "publishedTime": "2019-07-15T21:44:48.0Z",
      "ref": "v0.1.0"
    },
    "0.1.1": {
      "bytes": 12130,
      "hash": "sha256-WZ3MvRSOvDWII00ICm4JI1tunY7CfeQdnkx2WXmGvTE=",
      "publishedTime": "2019-07-16T21:33:35.0Z",
      "ref": "v0.1.1"
    },
    "0.2.0": {
      "bytes": 12152,
      "hash": "sha256-wtXJkg3d5ymAbY3akoJqVfEumNByg0A1bbOryLMriig=",
      "publishedTime": "2019-08-01T15:56:02.0Z",
      "ref": "v0.2.0"
    }
  },
  "unpublished": {}
}
