{
  "location": {
    "githubOwner": "purescript",
    "githubRepo": "purescript-lcg"
  },
  "published": {
    "1.0.0": {
      "bytes": 2841,
      "hash": "sha256-BiLHczcOQtxJsR1S8uXSDKqU0CBr00e1WXfnl22PL8o=",
      "publishedTime": "2017-11-07T15:50:44.0Z",
      "ref": "v1.0.0"
    },
    "2.0.0": {
      "bytes": 3026,
      "hash": "sha256-xfmXm05XRTwdDVDsUCvvl0a6gohC/DKclAyUStLtoGQ=",
      "publishedTime": "2018-05-23T00:24:27.0Z",
      "ref": "v2.0.0"
    },
    "3.0.0": {
      "bytes": 3879,
      "hash": "sha256-ko1hd+yuQboBMEqmnEos/fWRFPkzxUkHE/khnq1PxJA=",
      "publishedTime": "2021-02-26T18:50:48.0Z",
      "ref": "v3.0.0"
    },
    "4.0.0": {
      "bytes": 3981,
      "hash": "sha256-YvPHq7Tig4TmfxzK9wfARHiqj9VKWPmMcMyXrNEfCNo=",
      "publishedTime": "2022-04-27T19:46:03.0Z",
      "ref": "v4.0.0"
    }
  },
  "unpublished": {}
}