{
  "location": {
    "githubOwner": "purescript-node",
    "githubRepo": "purescript-posix-types"
  },
  "published": {
    "0.1.0": {
      "bytes": 2609,
      "hash": "sha256-JnvQW8JbzyB7C+vwxvZpYj/US6tvXYRgrlTODpofLiM=",
      "publishedTime": "2015-12-27T03:25:01.0Z",
      "ref": "v0.1.0"
    },
    "0.1.1": {
      "bytes": 2646,
      "hash": "sha256-urhYUg2PfEOaRMRZEdpSj/ayX/Zp/VPH15/MVF7yel0=",
      "publishedTime": "2015-12-27T03:31:42.0Z",
      "ref": "v0.1.1"
    },
    "1.0.0": {
      "bytes": 2635,
      "hash": "sha256-AHnvjH6tZ+QwX9Beg2MvS54aEnWO0kXIDgP+gQdwPPM=",
      "publishedTime": "2016-06-05T21:17:51.0Z",
      "ref": "v1.0.0"
    },
    "2.0.0": {
      "bytes": 2828,
      "hash": "sha256-upv6ZbYPKKQO4snHL8GBmMCARTxTvbl3TLnJxeLsjh8=",
      "publishedTime": "2016-10-21T22:57:43.0Z",
      "ref": "v2.0.0"
    },
    "3.0.0": {
      "bytes": 2820,
      "hash": "sha256-Xfy4CigtxVGQnW6Qr3AEIKYpgvQaLblnPSAthD7vbn4=",
      "publishedTime": "2017-04-04T03:57:17.0Z",
      "ref": "v3.0.0"
    },
    "4.0.0": {
      "bytes": 2812,
      "hash": "sha256-kqDEOvEEJAQD/QxB3Wb5EWTxPCs8WJ/CamjXD4rLVgs=",
      "publishedTime": "2018-05-26T13:30:22.0Z",
      "ref": "v4.0.0"
    },
    "5.0.0": {
      "bytes": 2856,
      "hash": "sha256-ko7VNtHmqNswZ6e3MYhGPzzuwsaT97crpdmqXXWrxPg=",
      "publishedTime": "2021-02-26T22:51:08.0Z",
      "ref": "v5.0.0"
    },
    "6.0.0": {
      "bytes": 2857,
      "hash": "sha256-HU/g/wCWOf/P5ovonSjlaJ09cKK2khYfATb/IjFw67E=",
      "publishedTime": "2022-04-27T19:12:48.0Z",
      "ref": "v6.0.0"
    }
  },
  "unpublished": {}
}
