{
  "location": {
    "githubOwner": "purescript-deprecated",
    "githubRepo": "purescript-react-addons-css-transition-group"
  },
  "published": {
    "0.1.0": {
      "bytes": 1979,
      "hash": "sha256-nb3Me9dOLNTFkHfCUWdbz+oSVcM73CDfSr5aGbwat8E=",
      "publishedTime": "2016-04-28T02:54:57.0Z",
      "ref": "v0.1.0"
    },
    "0.2.0": {
      "bytes": 1973,
      "hash": "sha256-26Y2rYxI5gu0nM6ZABJIKICBbkczlFewTaqdvz8XwvY=",
      "publishedTime": "2016-10-28T13:45:24.0Z",
      "ref": "v0.2.0"
    },
    "0.2.1": {
      "bytes": 2013,
      "hash": "sha256-80sjWZEea1BFmgRSw3MXruttZC8cADRDj9urkYlKBOM=",
      "publishedTime": "2016-10-28T20:50:20.0Z",
      "ref": "v0.2.1"
    }
  },
  "unpublished": {}
}
