{
  "location": {
    "githubOwner": "bodil",
    "githubRepo": "purescript-smolder-dom"
  },
  "published": {
    "1.0.0": {
      "bytes": 1906,
      "hash": "sha256-AqnARq/8kYeO4fwaMTXtBO82YWf+gyWSh7CIuo4v8/E=",
      "publishedTime": "2017-05-21T15:02:45.0Z",
      "ref": "v1.0.0"
    },
    "1.1.0": {
      "bytes": 3461,
      "hash": "sha256-YuhyheL4koMDWnAYUTB6NLepSwPsH9j3JfwPazQPegs=",
      "publishedTime": "2017-05-21T21:02:14.0Z",
      "ref": "v1.1.0"
    },
    "2.0.0": {
      "bytes": 4115,
      "hash": "sha256-I+WAaIAnlU4nGObHvbaArJOKpQMsXPjvTc7Kl1IlKL4=",
      "publishedTime": "2017-07-22T00:36:21.0Z",
      "ref": "v2.0.0"
    },
    "3.0.0": {
      "bytes": 4155,
      "hash": "sha256-DBh6fjekABkXBuMQwzfUIBsR8amKIwsrbvTx5ZxgYiI=",
      "publishedTime": "2018-10-11T13:01:22.0Z",
      "ref": "v3.0.0"
    }
  },
  "unpublished": {}
}
