{
  "location": {
    "githubOwner": "AlexMouton",
    "githubRepo": "purescript-split"
  },
  "published": {
    "0.1.0": {
      "bytes": 1828,
      "hash": "sha256-s7UUT4mrcmApZMPnOYj8oD0nqd8L3vE21VjAHaDQXPs=",
      "publishedTime": "2017-12-11T01:47:43.0Z",
      "ref": "v0.1.0"
    },
    "0.2.0": {
      "bytes": 1795,
      "hash": "sha256-iWgq6580XI7i5V06BzqX7MYHZ4+QAliQCdxcdw7XYDo=",
      "publishedTime": "2018-08-01T00:32:05.0Z",
      "ref": "v0.2.0"
    }
  },
  "unpublished": {}
}
