{
  "location": {
    "githubOwner": "joneshf",
    "githubRepo": "purescript-ui"
  },
  "published": {
    "0.1.0": {
      "bytes": 2000,
      "hash": "sha256-9dhVOy0PnvfglqtXtX2jD2VmMXcaL4DKwQVgfSl8oVI=",
      "publishedTime": "2015-02-21T20:28:47.0Z",
      "ref": "v0.1.0"
    },
    "0.1.1": {
      "bytes": 2114,
      "hash": "sha256-N+j0lXvpqrOAVBCL5wTS3e63K9TSfaoyGOR0BFYdKYY=",
      "publishedTime": "2015-02-21T23:21:41.0Z",
      "ref": "v0.1.1"
    },
    "0.1.2": {
      "bytes": 2765,
      "hash": "sha256-cfB5hsN5yG4XADDXYugC4h9RoWSCS2qAhXe+BUlCuZA=",
      "publishedTime": "2015-02-22T03:52:37.0Z",
      "ref": "v0.1.2"
    },
    "0.2.0": {
      "bytes": 4258,
      "hash": "sha256-4d/H0A64Xm8dXgWi+zFw2Hn7tcxe20GSRCQhTxV90PI=",
      "publishedTime": "2015-02-23T05:16:05.0Z",
      "ref": "v0.2.0"
    },
    "0.2.1": {
      "bytes": 5013,
      "hash": "sha256-3O/qf3kzZQESy4XqbCZYqTRFEkeXpuOSGl85kNohQGA=",
      "publishedTime": "2015-02-23T05:41:08.0Z",
      "ref": "v0.2.1"
    },
    "0.3.0": {
      "bytes": 6620,
      "hash": "sha256-+onPzuXl6/85bCIxlNT5h84X/TLlbcsnYr7J1ffTXXY=",
      "publishedTime": "2015-02-25T01:25:15.0Z",
      "ref": "v0.3.0"
    }
  },
  "unpublished": {}
}
