{
  "location": {
    "githubOwner": "cakekindel",
    "githubRepo": "purescript-workly"
  },
  "published": {
    "0.1.0": {
      "bytes": 7220,
      "hash": "sha256-JIUQTbCe73r8yr6my4M1qtSLAYnnb5Erl9W9B/zi7BM=",
      "publishedTime": "2021-03-18T21:39:14.0Z",
      "ref": "v0.1.0"
    },
    "0.1.1": {
      "bytes": 7209,
      "hash": "sha256-4/KLYovV63mESp00fFJypXGr7a+X54Av0tp8itQM1to=",
      "publishedTime": "2021-03-18T21:43:27.0Z",
      "ref": "v0.1.1"
    }
  },
  "unpublished": {}
}
